xontrib/jump_to_dir.py
xontrib_jump_to_dir-0.2.1.dist-info/LICENSE
xontrib_jump_to_dir-0.2.1.dist-info/METADATA
xontrib_jump_to_dir-0.2.1.dist-info/WHEEL
xontrib_jump_to_dir-0.2.1.dist-info/top_level.txt
xontrib_jump_to_dir-0.2.1.dist-info/RECORD
