Metadata-Version: 2.1
Name: xontrib-jump-to-dir
Version: 0.2.1
Summary: Jump to used before directory by part of the path. Lightweight zero-dependency implementation of autojump or zoxide projects functionality.
Author-email: anki-code <no@no.no>
License: MIT License
Project-URL: Homepage, https://github.com/anki-code/xontrib-jump-to-dir
Project-URL: Documentation, https://github.com/anki-code/xontrib-jump-to-dir/blob/master/README.md
Project-URL: Code, https://github.com/anki-code/xontrib-jump-to-dir
Project-URL: Issue tracker, https://github.com/anki-code/xontrib-jump-to-dir/issues
Platform: any
Classifier: Programming Language :: Python :: 3
Classifier: License :: OSI Approved :: MIT License
Classifier: Operating System :: OS Independent
Classifier: Topic :: System :: Shells
Classifier: Topic :: System :: System Shells
Classifier: Topic :: Terminals
Requires-Python: >=3.8
License-File: LICENSE
Requires-Dist: xonsh >=0.12.5
Provides-Extra: dev
Requires-Dist: pytest >=7.0 ; extra == 'dev'
